setup.py
fish_bundles/__init__.py
fish_bundles/version.py
fish_bundles.egg-info/PKG-INFO
fish_bundles.egg-info/SOURCES.txt
fish_bundles.egg-info/dependency_links.txt
fish_bundles.egg-info/entry_points.txt
fish_bundles.egg-info/requires.txt
fish_bundles.egg-info/top_level.txt
fish_bundles/cli/__init__.py
fish_bundles/cli/init.py
fish_bundles/cli/install.py
fish_bundles/cli/list.py
fish_bundles/cli/lock.py
tests/__init__.py
tests/base.py
tests/test_version.py