Metadata-Version: 1.1
Name: fish-bundles
Version: 0.1.0
Summary: fb is the command line tool for fish-bundles
Home-page: https://github.com/fish-bundles/fb
Author: Bernardo Heynemann
Author-email: heynemann@gmail.com
License: MIT
Keywords: fish fish-bundles cli shell
Platform: UNKNOWN
Classifier: Development Status :: 4 - Beta
Classifier: Intended Audience :: Developers
Classifier: License :: OSI Approved :: MIT License
Classifier: Natural Language :: English
Classifier: Operating System :: Unix
Classifier: Programming Language :: Python :: 2.7
Classifier: Programming Language :: Python :: 3.4
Classifier: Programming Language :: Python :: Implementation :: PyPy
Classifier: Operating System :: OS Independent
